zabbix_utils/__init__.py
zabbix_utils/aioapi.py
zabbix_utils/aiogetter.py
zabbix_utils/aiosender.py
zabbix_utils/api.py
zabbix_utils/common.py
zabbix_utils/exceptions.py
zabbix_utils/getter.py
zabbix_utils/logger.py
zabbix_utils/sender.py
zabbix_utils/status.py
zabbix_utils/types.py
zabbix_utils/version.py
zabbix_utils-2.0.3.dist-info/LICENSE
zabbix_utils-2.0.3.dist-info/METADATA
zabbix_utils-2.0.3.dist-info/WHEEL
zabbix_utils-2.0.3.dist-info/top_level.txt
zabbix_utils-2.0.3.dist-info/RECORD
