Metadata-Version: 2.1
Name: zabbix_utils
Version: 2.0.3
Summary: A library with modules for working with Zabbix (Zabbix API, Zabbix sender, Zabbix get)
Home-page: https://github.com/zabbix/python-zabbix-utils
Author: Zabbix SIA
Author-email: integrationteam@zabbix.com
Maintainer: Aleksandr Iantsen
Maintainer-email: aleksandr.iantsen@zabbix.com
Project-URL: Zabbix, https://www.zabbix.com/documentation/current
Project-URL: Source, https://github.com/zabbix/python-zabbix-utils
Project-URL: Changes, https://github.com/zabbix/python-zabbix-utils/blob/main/CHANGELOG.md
Project-URL: Bug Tracker, https://github.com/zabbix/python-zabbix-utils/issues
Keywords: monitoring zabbix api sender get utils tools
Classifier: Development Status :: 5 - Production/Stable
Classifier: Programming Language :: Python
Classifier: Programming Language :: Python :: 3
Classifier: Programming Language :: Python :: 3.8
Classifier: Programming Language :: Python :: 3.9
Classifier: Programming Language :: Python :: 3.10
Classifier: Programming Language :: Python :: 3.11
Classifier: Programming Language :: Python :: 3.12
Classifier: Programming Language :: Python :: 3.13
Classifier: License :: OSI Approved :: MIT License
Classifier: Operating System :: OS Independent
Classifier: Topic :: System :: Monitoring
Classifier: Topic :: System :: Networking :: Monitoring
Classifier: Topic :: System :: Systems Administration
Classifier: Intended Audience :: Developers
Classifier: Intended Audience :: System Administrators
Classifier: Intended Audience :: Information Technology
Requires-Python: >=3.8
Provides-Extra: async
License-File: LICENSE
